tests/__init__.py
tests/test_audio_samples.py
tests/test_basic.py
tests/test_device_functionality.py
tests/test_preprocessing_functions.py
tests/test_preprocessing_pipeline.py
tests/test_silence_detection_comprehensive.py
tests/test_utils.py
tests/utils.py
voxlab/__init__.py
voxlab/core/__init__.py
voxlab/core/audio_samples.py
voxlab/embedding/__init__.py
voxlab/embedding/extractor.py
voxlab/preprocessing/__init__.py
voxlab/preprocessing/functions.py
voxlab/preprocessing/pipeline.py
voxlab/preprocessing/range_covering_functions.py
voxlab-0.3.7.dist-info/licenses/LICENSE
voxlab-0.3.7.dist-info/METADATA
voxlab-0.3.7.dist-info/WHEEL
voxlab-0.3.7.dist-info/top_level.txt
voxlab-0.3.7.dist-info/RECORD
