Metadata-Version: 2.4
Name: voxlab
Version: 0.3.7
Summary: A comprehensive Python toolbox for audio processing using PyTorch with device-aware operations and GPU acceleration.
Home-page: https://github.com/rvirgilli/voxlab
Author: Rafaello Virgilli
Author-email: rvirgilli@gmail.com
Keywords: audio processing,pytorch,torchaudio,signal processing,gpu acceleration
Classifier: Development Status :: 4 - Beta
Classifier: Intended Audience :: Developers
Classifier: Intended Audience :: Science/Research
Classifier: Topic :: Scientific/Engineering :: Artificial Intelligence
Classifier: Topic :: Multimedia :: Sound/Audio :: Analysis
Classifier: License :: OSI Approved :: MIT License
Classifier: Programming Language :: Python :: 3
Classifier: Programming Language :: Python :: 3.11
Classifier: Operating System :: OS Independent
Requires-Python: >=3.11
License-File: LICENSE
Requires-Dist: torch>=2.8.0
Requires-Dist: torchaudio>=2.8.0
Requires-Dist: scipy>=1.16.2
Requires-Dist: numpy>=2.1.2
Requires-Dist: pytest>=8.4.2
Requires-Dist: librosa>=0.10.0
Dynamic: author
Dynamic: author-email
Dynamic: classifier
Dynamic: description
Dynamic: description-content-type
Dynamic: home-page
Dynamic: keywords
Dynamic: license-file
Dynamic: requires-dist
Dynamic: requires-python
Dynamic: summary
